MANIFEST.in
README.md
setup.cfg
setup.py
rest_frameworkws/__init__.py
rest_frameworkws/admin.py
rest_frameworkws/authentication.py
rest_frameworkws/exceptions.py
rest_frameworkws/models.py
rest_frameworkws/permissions.py
rest_frameworkws/serializers.py
rest_frameworkws/settings.py
rest_frameworkws/urls.py
rest_frameworkws/views.py
rest_frameworkws.egg-info/PKG-INFO
rest_frameworkws.egg-info/SOURCES.txt
rest_frameworkws.egg-info/dependency_links.txt
rest_frameworkws.egg-info/requires.txt
rest_frameworkws.egg-info/top_level.txt